{
  "schemaVersion": 1,
  "id": "bactromod",
  "authors": ["Bactrosaurus", "FurnyGo"],
  "description": "A lightweight mod with some game optimizations and features.",
  "version": "2.6",
  "name": "BactroMod",
  "environment": "client",
  "license": "LGPL-3.0-only",
  "icon": "assets/bactromod/icon.png",
  "entrypoints": {
    "client": ["de.daniel.bactromod.BactroModKt::init"],
    "modmenu": [ "de.daniel.bactromod.impl.ModMenuIntegration"]
  },
  "mixins": [
    "bactromod.mixins.json"
  ],
  "accessWidener" : "bactromod.accesswidener",
  "depends": {
    "fabricloader": ">=0.16.9",
    "fabric-language-kotlin": ">=1.12.3+kotlin.2.0.21",
    "minecraft": ">=1.21.3"
  }
}